{
  "tipo": "Saída",
  "total_real": 589.49,
  "total_extraido": 429.49,
  "diferenca": 160.0,
  "transacoes": [
    {
      "data": "07/05/2025",
      "descricao": "Transferência enviada pelo Pix Henrique Jesus Freitas Pereira - .819.117-",
      "valor": 70.0,
      "tipo_transacao": "Saída",
      "categoria_sugerida": "Transferências",
      "subcategoria_sugerida": "PIX Enviado (Terceiros)"
    },
    {
      "data": "08/05/2025",
      "descricao": "Transferência enviada pelo Pix MARIA DEUSINHA FEITOSA RIBEIRO 09269558703 - 34.595.290/0001-85 - STONE IP S.A. (0197) Agência: 1 Conta: 5107666-9",
      "valor": 3.0,
      "tipo_transacao": "Saída",
      "categoria_sugerida": "Transferências",
      "subcategoria_sugerida": "PIX Enviado (Terceiros)"
    },
    {
      "data": "15/05/2025",
      "descricao": "Transferência enviada pelo Pix KAIZEN GAMING BRASIL LTDA - 46.786.961/0001-74 - BANCO BTG PACTUAL S.A. (0208) Agência: 30 Conta: 567491-0",
      "valor": 40.0,
      "tipo_transacao": "Saída",
      "categoria_sugerida": "Transferências",
      "subcategoria_sugerida": "PIX Enviado (Terceiros)"
    },
    {
      "data": "15/05/2025",
      "descricao": "Transferência enviada pelo Pix HS DO BRASIL LTDA - 47.123.407/0001-70 - PAGSEGURO INTERNET IP S.A. (0290) Agência: 1 Conta: 78418804-7",
      "valor": 80.0,
      "tipo_transacao": "Saída",
      "categoria_sugerida": "Transferências",
      "subcategoria_sugerida": "PIX Enviado (Terceiros)"
    },
    {
      "data": "01/05/2025 a 31/05/2025",
      "descricao": "Pagamento de fatura",
      "valor": 157.49,
      "tipo_transacao": "Saída",
      "categoria_sugerida": "Financeiro",
      "subcategoria_sugerida": "Pagamento de Fatura Cartão"
    },
    {
      "data": "19/05/2025",
      "descricao": "Transferência enviada pelo Pix S M C SORVETES - 58.569.343/0001-51 - ITAÚ UNIBANCO S.A. (0341) Agência: 6021 Conta: 99054-1",
      "valor": 4.0,
      "tipo_transacao": "Saída",
      "categoria_sugerida": "Alimentação",
      "subcategoria_sugerida": "Padaria e Lanches"
    },
    {
      "data": "24/05/2025",
      "descricao": "Transferência enviada pelo Pix KAIZEN GAMING BRASIL LTDA - 46.786.961/0001- 25,00\n74 - BANCO BTG PACTUAL S.A. (0208) Agência:\n30 Conta: 567491-0",
      "valor": 25.0,
      "tipo_transacao": "Saída",
      "categoria_sugerida": "Transferências",
      "subcategoria_sugerida": "PIX Enviado (Terceiros)"
    },
    {
      "data": "31/05/2025",
      "descricao": "Transferência enviada pelo Pix KAIZEN GAMING BRASIL LTDA - 46.786.961/0001-",
      "valor": 50.0,
      "tipo_transacao": "Saída",
      "categoria_sugerida": "Transferências",
      "subcategoria_sugerida": "PIX Enviado (Terceiros)"
    }
  ]
}